grpc_client/__init__.py
grpc_client/client.py
proto_parsers/__init__.py
proto_parsers/sqltest_parser.py
synq_tests/__init__.py
synq_tests/create_sql_tests.py
synq_infra_management-0.4.1.dist-info/METADATA
synq_infra_management-0.4.1.dist-info/WHEEL
synq_infra_management-0.4.1.dist-info/dependency_links.txt
synq_infra_management-0.4.1.dist-info/top_level.txt
synq_infra_management-0.4.1.dist-info/RECORD
