Metadata-Version: 2.4
Name: synq_infra_management
Version: 0.4.1
Summary: A package to compare and manage Synq SQL tests from YAML files
Home-page: https://github.com/IAG-Loyalty/synq-infra-management/synq_infra_management
Author: Bruno Farias
Author-email: bruno.farias@avios.com
Classifier: Programming Language :: Python :: 3
Classifier: Operating System :: OS Independent
Requires-Python: >=3.8
Requires-Dist: getsynq-api-grpc-python
Requires-Dist: grpcio
Requires-Dist: grpcio-tools
Requires-Dist: requests_oauthlib
Requires-Dist: PyYAML
Dynamic: author
Dynamic: author-email
Dynamic: classifier
Dynamic: home-page
Dynamic: requires-dist
Dynamic: requires-python
Dynamic: summary
